CODE_OF_CONDUCT.md
CONTRIBUTING.md
Changelog.rst
LICENSE
MANIFEST.in
README.md
pyproject.toml
requirements.txt
setup.py
cfdm/__init__.py
cfdm/auxiliarycoordinate.py
cfdm/bounds.py
cfdm/cellconnectivity.py
cfdm/cellmeasure.py
cfdm/cellmethod.py
cfdm/cfdmimplementation.py
cfdm/constants.py
cfdm/constructs.py
cfdm/coordinateconversion.py
cfdm/coordinatereference.py
cfdm/count.py
cfdm/datum.py
cfdm/decorators.py
cfdm/dimensioncoordinate.py
cfdm/domain.py
cfdm/domainancillary.py
cfdm/domainaxis.py
cfdm/domaintopology.py
cfdm/examplefield.py
cfdm/field.py
cfdm/fieldancillary.py
cfdm/functions.py
cfdm/index.py
cfdm/interiorring.py
cfdm/interpolationparameter.py
cfdm/list.py
cfdm/nodecountproperties.py
cfdm/partnodecountproperties.py
cfdm/quantization.py
cfdm/tiepointindex.py
cfdm/units.py
cfdm.egg-info/PKG-INFO
cfdm.egg-info/SOURCES.txt
cfdm.egg-info/dependency_links.txt
cfdm.egg-info/requires.txt
cfdm.egg-info/top_level.txt
cfdm/abstract/__init__.py
cfdm/abstract/container.py
cfdm/abstract/implementation.py
cfdm/core/__init__.py
cfdm/core/auxiliarycoordinate.py
cfdm/core/bounds.py
cfdm/core/cellconnectivity.py
cfdm/core/cellmeasure.py
cfdm/core/cellmethod.py
cfdm/core/constructs.py
cfdm/core/coordinateconversion.py
cfdm/core/coordinatereference.py
cfdm/core/datum.py
cfdm/core/dimensioncoordinate.py
cfdm/core/domain.py
cfdm/core/domainancillary.py
cfdm/core/domainaxis.py
cfdm/core/domaintopology.py
cfdm/core/field.py
cfdm/core/fieldancillary.py
cfdm/core/functions.py
cfdm/core/interiorring.py
cfdm/core/utils.py
cfdm/core/abstract/__init__.py
cfdm/core/abstract/container.py
cfdm/core/abstract/coordinate.py
cfdm/core/abstract/parameters.py
cfdm/core/abstract/parametersdomainancillaries.py
cfdm/core/abstract/properties.py
cfdm/core/abstract/propertiesdata.py
cfdm/core/abstract/propertiesdatabounds.py
cfdm/core/abstract/topology.py
cfdm/core/data/__init__.py
cfdm/core/data/data.py
cfdm/core/data/numpyarray.py
cfdm/core/data/abstract/__init__.py
cfdm/core/data/abstract/array.py
cfdm/core/docstring/__init__.py
cfdm/core/docstring/docstring.py
cfdm/core/meta/__init__.py
cfdm/core/meta/docstringrewrite.py
