Metadata-Version: 2.4
Name: cfdm
Version: 1.13.0.0
Summary: A Python reference implementation of the CF data model
Home-page: https://ncas-cms.github.io/cfdm
Download-URL: https://pypi.org/project/cfdm/#files
Author: David Hassell, Sadie Bartholomew
Author-email: david.hassell@ncas.ac.uk
Maintainer: David Hassell, Sadie Bartholomew
License: MIT
Keywords: cf,netcdf,data,science,oceanography,meteorology,climate
Platform: Linux
Platform: MacOS
Platform: Windows
Classifier: Development Status :: 5 - Production/Stable
Classifier: Intended Audience :: Science/Research
Classifier: License :: OSI Approved :: MIT License
Classifier: Topic :: Software Development
Classifier: Topic :: Scientific/Engineering
Classifier: Operating System :: OS Independent
Classifier: Programming Language :: Python
Classifier: Programming Language :: Python :: 3
Classifier: Programming Language :: Python :: 3.10
Classifier: Programming Language :: Python :: 3.11
Classifier: Programming Language :: Python :: 3.12
Classifier: Programming Language :: Python :: 3.13
Requires-Python: >=3.10
License-File: LICENSE
Requires-Dist: netCDF4>=1.7.2
Requires-Dist: cftime>=1.6.4
Requires-Dist: numpy>=2.0.0
Requires-Dist: packaging>=20.0
Requires-Dist: scipy>=1.10.0
Requires-Dist: h5netcdf>=1.3.0
Requires-Dist: h5py>=3.12.0
Requires-Dist: s3fs>=2024.6.0
Requires-Dist: dask>=2025.5.1
Requires-Dist: distributed>=2025.5.1
Requires-Dist: uritools>=4.0.3
Requires-Dist: cfunits>=3.3.7
Provides-Extra: documentation
Requires-Dist: sphinx>=7.0.0; extra == "documentation"
Requires-Dist: sphinx-copybutton; extra == "documentation"
Requires-Dist: sphinx-toggleprompt; extra == "documentation"
Requires-Dist: sphinxcontrib-spelling; extra == "documentation"
Provides-Extra: pre-commit-hooks
Requires-Dist: pre-commit; extra == "pre-commit-hooks"
Requires-Dist: black; extra == "pre-commit-hooks"
Requires-Dist: docformatter; extra == "pre-commit-hooks"
Requires-Dist: flake8; extra == "pre-commit-hooks"
Requires-Dist: pydocstyle; extra == "pre-commit-hooks"
Provides-Extra: zarr
Requires-Dist: zarr>=3.1.3; extra == "zarr"
Dynamic: author
Dynamic: author-email
Dynamic: classifier
Dynamic: description
Dynamic: description-content-type
Dynamic: download-url
Dynamic: home-page
Dynamic: keywords
Dynamic: license
Dynamic: license-file
Dynamic: maintainer
Dynamic: platform
Dynamic: provides-extra
Dynamic: requires-dist
Dynamic: requires-python
Dynamic: summary
